Metadata-Version: 1.0
Name: mmc-distributions
Version: 0.1
Summary: Probability distributions
Home-page: UNKNOWN
Author: Michael McMahon
Author-email: michael-mcmahon94@hotmail.com
License: UNKNOWN
Platform: UNKNOWN
